gram_pytools-0.2.4.dist-info/METADATA
gram_pytools-0.2.4.dist-info/WHEEL
gram_pytools/__init__.py
gram_pytools/__init__.pyi
gram_pytools/gram_pytools.cpython-311-i386-linux-gnu.so
gram_pytools/py.typed
gram_pytools-0.2.4.dist-info/RECORD
